{
  "urn" : "local:ferdinando.villa:testproject1:aries.eu_cfactor_final_v7",
  "version" : "0.0.1",
  "adapterType" : "wcs",
  "localPath" : "testproject1/resources/aries.eu_cfactor_final_v7",
  "geometry" : "S2(58999,45999){bbox=[-180.0 180.0 25.54471118562295 72.63149272041737],proj=EPSG:4326}",
  "projectName" : "testproject1",
  "localName" : "aries.eu_cfactor_final_v7",
  "type" : "NUMBER",
  "resourceTimestamp" : 1534598297327,
  "metadata" : { },
  "parameters" : {
    "wcsIdentifier" : "aries__EU_CFactor_final_V7",
    "serviceUrl" : "http://150.241.222.1/geoserver/ows",
    "nodata" : "-3.4028234663852886E38",
    "wcsVersion" : "2.0.1"
  },
  "localPaths" : [ ],
  "history" : [ ],
  "notifications" : [ ],
  "spatialExtent" : {
    "east" : 180.0,
    "west" : -180.0,
    "north" : 72.63149272041737,
    "south" : 25.54471118562295
  }
}